JvmBizhiBihui/README.md
JvmBizhiBihui/__init__.py
JvmBizhiBihui/__main__.py
JvmBizhiBihui/file.epub
JvmBizhiBihui/index.html
JvmBizhiBihui/css/__init__.py
JvmBizhiBihui/css/annotations.css
JvmBizhiBihui/css/main.css
JvmBizhiBihui/css/normalize.css
JvmBizhiBihui/css/popup.css
JvmBizhiBihui/font/__init__.py
JvmBizhiBihui/font/fontello.eot
JvmBizhiBihui/font/fontello.svg
JvmBizhiBihui/font/fontello.ttf
JvmBizhiBihui/font/fontello.woff
JvmBizhiBihui/img/__init__.py
JvmBizhiBihui/img/annotator-glyph-sprite.png
JvmBizhiBihui/img/annotator-icon-sprite.png
JvmBizhiBihui/img/apple-touch-icon.png
JvmBizhiBihui/img/cancelfullscreen.png
JvmBizhiBihui/img/close.png
JvmBizhiBihui/img/fullscreen.png
JvmBizhiBihui/img/loader.gif
JvmBizhiBihui/img/menu-icon.png
JvmBizhiBihui/img/save.png
JvmBizhiBihui/img/saved.png
JvmBizhiBihui/img/settings-s.png
JvmBizhiBihui/img/settings.png
JvmBizhiBihui/img/star.png
JvmBizhiBihui/js/__init__.py
JvmBizhiBihui/js/epub.js
JvmBizhiBihui/js/epub.min.js
JvmBizhiBihui/js/epub.min.map
JvmBizhiBihui/js/hooks.min.js
JvmBizhiBihui/js/hooks.min.map
JvmBizhiBihui/js/reader.js
JvmBizhiBihui/js/reader.js.map
JvmBizhiBihui/js/reader.min.js
JvmBizhiBihui/js/reader.min.map
JvmBizhiBihui/js/hooks/__init__.py
JvmBizhiBihui/js/hooks/extensions/__init__.py
JvmBizhiBihui/js/hooks/extensions/highlight.js
JvmBizhiBihui/js/libs/__init__.py
JvmBizhiBihui/js/libs/jquery.min.js
JvmBizhiBihui/js/libs/localforage.min.js
JvmBizhiBihui/js/libs/screenfull.js
JvmBizhiBihui/js/libs/screenfull.min.js
JvmBizhiBihui/js/libs/zip.min.js
JvmBizhiBihui/js/plugins/__init__.py
JvmBizhiBihui/js/plugins/hypothesis.js
JvmBizhiBihui/js/plugins/search.js
jvm_bizhi_bihui-2024.3.3.0.dist-info/METADATA
jvm_bizhi_bihui-2024.3.3.0.dist-info/WHEEL
jvm_bizhi_bihui-2024.3.3.0.dist-info/entry_points.txt
jvm_bizhi_bihui-2024.3.3.0.dist-info/top_level.txt
jvm_bizhi_bihui-2024.3.3.0.dist-info/RECORD
